README.md
setup.py
JanexUltimate/__init__.py
JanexUltimate/janexnlg.py
JanexUltimate/janexpython.py
JanexUltimate/janexpytorch.py
JanexUltimate/janexspacy.py
JanexUltimate/main.py
JanexUltimate.egg-info/PKG-INFO
JanexUltimate.egg-info/SOURCES.txt
JanexUltimate.egg-info/dependency_links.txt
JanexUltimate.egg-info/requires.txt
JanexUltimate.egg-info/top_level.txt