Metadata-Version: 2.1
Name: JanexUltimate
Version: 0.1.7
Summary: A description of your package
Home-page: https://github.com/ChronoByte404/Janex-Ultimate
Author: ChronoByte404
Author-email: cipher58public@gmail.com
License: Lily 3.0
Classifier: Programming Language :: Python :: 3
Classifier: Operating System :: OS Independent
Requires-Dist: CipherProgram
Requires-Dist: torch
Requires-Dist: nltk
Requires-Dist: spacy
